{
  "metadata": {
    "source_kind": "AnsibleBase"
  },
  "graph": {
    "nodes": [
      {
        "id": "b4daac53-5735-4ba7-b4ca-9fa4aa4285cd",
        "kinds": [
          "ATUser"
        ],
        "properties": {
          "description": "",
          "email": "test@example.com",
          "external_account": "",
          "firstname": "",
          "id": "1",
          "is_super_user": "true",
          "is_system_auditor": "false",
          "last_login": "2025-07-30T20:56:42.050068Z",
          "lastname": "",
          "ldap_dn": "",
          "name": "admin",
          "url": "/api/v2/users/1/"
        }
      },
      {
        "id": "616715cc-1f67-445c-9318-d27c9ece349c",
        "kinds": [
          "ATUser"
        ],
        "properties": {
          "description": "",
          "email": "",
          "external_account": "",
          "firstname": "Alice",
          "id": "92",
          "is_super_user": "false",
          "is_system_auditor": "false",
          "last_login": "",
          "lastname": "",
          "ldap_dn": "",
          "name": "alice",
          "url": "/api/v2/users/92/"
        }
      },
      {
        "id": "126f49af-f1bb-4226-951c-09e2089964ed",
        "kinds": [
          "ATUser"
        ],
        "properties": {
          "description": "",
          "email": "",
          "external_account": "",
          "firstname": "Bob",
          "id": "93",
          "is_super_user": "false",
          "is_system_auditor": "false",
          "last_login": "",
          "lastname": "",
          "ldap_dn": "",
          "name": "bob",
          "url": "/api/v2/users/93/"
        }
      },
      {
        "id": "89ba387b-501f-4845-b5c9-0000fd1a1892",
        "kinds": [
          "ATUser"
        ],
        "properties": {
          "description": "",
          "email": "",
          "external_account": "",
          "firstname": "Joe",
          "id": "94",
          "is_super_user": "false",
          "is_system_auditor": "false",
          "last_login": "",
          "lastname": "",
          "ldap_dn": "",
          "name": "joe",
          "url": "/api/v2/users/94/"
        }
      },
      {
        "id": "5b91f087-b5c2-46fd-9402-8c5b54476d01",
        "kinds": [
          "ATUser"
        ],
        "properties": {
          "description": "",
          "email": "",
          "external_account": "",
          "firstname": "Karen",
          "id": "96",
          "is_super_user": "false",
          "is_system_auditor": "false",
          "last_login": "",
          "lastname": "",
          "ldap_dn": "",
          "name": "karen",
          "url": "/api/v2/users/96/"
        }
      },
      {
        "id": "8f640911-fded-4256-bfab-931979024741",
        "kinds": [
          "ATUser"
        ],
        "properties": {
          "description": "",
          "email": "",
          "external_account": "",
          "firstname": "Kyle",
          "id": "95",
          "is_super_user": "false",
          "is_system_auditor": "false",
          "last_login": "2025-07-30T20:23:47.670612Z",
          "lastname": "",
          "ldap_dn": "",
          "name": "kyle",
          "url": "/api/v2/users/95/"
        }
      },
      {
        "id": "5f8bc352-f182-46d6-aa0e-ba61f1adb6ed",
        "kinds": [
          "ATHost"
        ],
        "properties": {
          "ansible_facts_modified": "",
          "created": "2025-07-30T19:51:04.648465Z",
          "description": "",
          "enabled": "true",
          "has_active_failures": "false",
          "id": "513",
          "instance_id": "",
          "inventory": "74",
          "last_job": "0",
          "last_job_host_summary": "0",
          "modified": "2025-07-30T19:51:04.648481Z",
          "name": "dev-01.example.tld",
          "type": "host",
          "url": "/api/v2/hosts/513/",
          "variables": "---"
        }
      },
      {
        "id": "c2218a01-9d66-4ab0-a449-76bfebd957a3",
        "kinds": [
          "ATHost"
        ],
        "properties": {
          "ansible_facts_modified": "",
          "created": "2025-07-30T19:51:13.590893Z",
          "description": "",
          "enabled": "true",
          "has_active_failures": "false",
          "id": "514",
          "instance_id": "",
          "inventory": "74",
          "last_job": "0",
          "last_job_host_summary": "0",
          "modified": "2025-07-30T19:51:13.590901Z",
          "name": "dev-02.example.tld",
          "type": "host",
          "url": "/api/v2/hosts/514/",
          "variables": "---"
        }
      },
      {
        "id": "a4ae8ed6-e803-49cb-92f9-ab51fc747f04",
        "kinds": [
          "ATHost"
        ],
        "properties": {
          "ansible_facts_modified": "",
          "created": "2025-07-30T20:15:12.523320Z",
          "description": "",
          "enabled": "true",
          "has_active_failures": "false",
          "id": "515",
          "instance_id": "",
          "inventory": "75",
          "last_job": "0",
          "last_job_host_summary": "0",
          "modified": "2025-07-30T20:15:12.523328Z",
          "name": "prod-01.example.tld",
          "type": "host",
          "url": "/api/v2/hosts/515/",
          "variables": "---"
        }
      },
      {
        "id": "2363b88b-1009-4e61-aecc-c1d55e90d0dc",
        "kinds": [
          "ATHost"
        ],
        "properties": {
          "ansible_facts_modified": "",
          "created": "2025-07-30T20:15:30.807967Z",
          "description": "",
          "enabled": "true",
          "has_active_failures": "false",
          "id": "516",
          "instance_id": "",
          "inventory": "75",
          "last_job": "0",
          "last_job_host_summary": "0",
          "modified": "2025-07-30T20:15:30.807974Z",
          "name": "prod-02.example.tld",
          "type": "host",
          "url": "/api/v2/hosts/516/",
          "variables": "---"
        }
      },
      {
        "id": "e6cea985-10ce-447f-b487-7e7cf0f4960d",
        "kinds": [
          "ATHost"
        ],
        "properties": {
          "ansible_facts_modified": "",
          "created": "2025-07-30T20:15:46.525818Z",
          "description": "",
          "enabled": "true",
          "has_active_failures": "false",
          "id": "517",
          "instance_id": "",
          "inventory": "75",
          "last_job": "0",
          "last_job_host_summary": "0",
          "modified": "2025-07-30T20:15:55.679546Z",
          "name": "prod-backup.example.tld",
          "type": "host",
          "url": "/api/v2/hosts/517/",
          "variables": "---"
        }
      },
      {
        "id": "bbf3d527-f825-46fe-b24e-cc38fa083856",
        "kinds": [
          "ATJobTemplate"
        ],
        "properties": {
          "allow_simultaneous": "false",
          "ask_credential_on_launch": "false",
          "ask_diff_mode_on_launch": "false",
          "ask_execution_environment_on_launch": "false",
          "ask_forks_on_launch": "false",
          "ask_instance_groups_on_launch": "false",
          "ask_inventory_on_launch": "false",
          "ask_job_slice_count_on_launch": "false",
          "ask_job_type_on_launch": "false",
          "ask_labels_on_launch": "false",
          "ask_limit_on_launch": "false",
          "ask_scm_branch_on_launch": "false",
          "ask_tags_on_launch": "false",
          "ask_timeout_on_launch": "false",
          "ask_variables_on_launch": "false",
          "ask_verbosity_on_launch": "false",
          "become_enabled": "false",
          "custom_virtualenv": "",
          "description": "",
          "diff_mode": "false",
          "execution_environment": "0",
          "extra_vars": "---",
          "force_handler": "false",
          "forks": "0",
          "host_config_key": "",
          "id": "91",
          "job_slice_count": "1",
          "job_tags": "",
          "job_type": "run",
          "last_job_failed": "false",
          "last_job_run": "",
          "limit": "prod-backup.example.tld",
          "name": "Backup Prod",
          "next_job_run": "",
          "organization": "15",
          "playbook": "helloworld.yml",
          "prevent_instance_group_fallback": "false",
          "project": "88",
          "scm_branch": "",
          "skip_tags": "",
          "start_at_task": "",
          "status": "never updated",
          "survey_enabled": "false",
          "timeout": "0",
          "url": "/api/v2/job_templates/91/",
          "use_fact_cache": "false",
          "verbosity": "0",
          "webhook_credential": "0",
          "webhook_service": ""
        }
      },
      {
        "id": "bd1c786c-a802-4fe5-ba40-3e457415cf96",
        "kinds": [
          "ATJobTemplate"
        ],
        "properties": {
          "allow_simultaneous": "false",
          "ask_credential_on_launch": "false",
          "ask_diff_mode_on_launch": "false",
          "ask_execution_environment_on_launch": "false",
          "ask_forks_on_launch": "false",
          "ask_instance_groups_on_launch": "false",
          "ask_inventory_on_launch": "false",
          "ask_job_slice_count_on_launch": "false",
          "ask_job_type_on_launch": "false",
          "ask_labels_on_launch": "false",
          "ask_limit_on_launch": "true",
          "ask_scm_branch_on_launch": "false",
          "ask_tags_on_launch": "false",
          "ask_timeout_on_launch": "false",
          "ask_variables_on_launch": "true",
          "ask_verbosity_on_launch": "false",
          "become_enabled": "false",
          "custom_virtualenv": "",
          "description": "",
          "diff_mode": "false",
          "execution_environment": "0",
          "extra_vars": "---",
          "force_handler": "false",
          "forks": "0",
          "host_config_key": "",
          "id": "89",
          "job_slice_count": "1",
          "job_tags": "",
          "job_type": "run",
          "last_job_failed": "false",
          "last_job_run": "",
          "limit": "",
          "name": "Deploy Dev",
          "next_job_run": "",
          "organization": "14",
          "playbook": "helloworld.yml",
          "prevent_instance_group_fallback": "false",
          "project": "86",
          "scm_branch": "",
          "skip_tags": "",
          "start_at_task": "",
          "status": "never updated",
          "survey_enabled": "false",
          "timeout": "0",
          "url": "/api/v2/job_templates/89/",
          "use_fact_cache": "false",
          "verbosity": "0",
          "webhook_credential": "0",
          "webhook_service": ""
        }
      },
      {
        "id": "f4e5ba05-167e-4cae-a4fd-852976dafc79",
        "kinds": [
          "ATJobTemplate"
        ],
        "properties": {
          "allow_simultaneous": "false",
          "ask_credential_on_launch": "false",
          "ask_diff_mode_on_launch": "false",
          "ask_execution_environment_on_launch": "false",
          "ask_forks_on_launch": "false",
          "ask_instance_groups_on_launch": "false",
          "ask_inventory_on_launch": "false",
          "ask_job_slice_count_on_launch": "false",
          "ask_job_type_on_launch": "false",
          "ask_labels_on_launch": "false",
          "ask_limit_on_launch": "false",
          "ask_scm_branch_on_launch": "false",
          "ask_tags_on_launch": "false",
          "ask_timeout_on_launch": "false",
          "ask_variables_on_launch": "false",
          "ask_verbosity_on_launch": "false",
          "become_enabled": "false",
          "custom_virtualenv": "",
          "description": "",
          "diff_mode": "false",
          "execution_environment": "0",
          "extra_vars": "---",
          "force_handler": "false",
          "forks": "0",
          "host_config_key": "",
          "id": "90",
          "job_slice_count": "1",
          "job_tags": "",
          "job_type": "run",
          "last_job_failed": "false",
          "last_job_run": "",
          "limit": "",
          "name": "Deploy Prod",
          "next_job_run": "",
          "organization": "15",
          "playbook": "helloworld.yml",
          "prevent_instance_group_fallback": "false",
          "project": "87",
          "scm_branch": "",
          "skip_tags": "",
          "start_at_task": "",
          "status": "never updated",
          "survey_enabled": "false",
          "timeout": "0",
          "url": "/api/v2/job_templates/90/",
          "use_fact_cache": "false",
          "verbosity": "0",
          "webhook_credential": "0",
          "webhook_service": ""
        }
      },
      {
        "id": "e8d539b4-6435-407b-805f-20ce2723e272",
        "kinds": [
          "ATInventory"
        ],
        "properties": {
          "description": "",
          "has_active_failures": "false",
          "has_inventory_source": "false",
          "host_filter": "",
          "hosts_with_active_failures": "0",
          "id": "74",
          "inventory_sources_with_failures": "0",
          "kind": "",
          "name": "Dev",
          "organization": "14",
          "pending_deletion": "false",
          "prevent_instance_group_fallback": "false",
          "total_groups": "0",
          "total_hosts": "2",
          "total_inventory_sources": "0",
          "url": "/api/v2/inventories/74/"
        }
      },
      {
        "id": "2c4eeb63-0cf3-421d-bd13-3ec5eb5d6918",
        "kinds": [
          "ATInventory"
        ],
        "properties": {
          "description": "",
          "has_active_failures": "false",
          "has_inventory_source": "false",
          "host_filter": "",
          "hosts_with_active_failures": "0",
          "id": "75",
          "inventory_sources_with_failures": "0",
          "kind": "",
          "name": "Prod",
          "organization": "15",
          "pending_deletion": "false",
          "prevent_instance_group_fallback": "false",
          "total_groups": "0",
          "total_hosts": "3",
          "total_inventory_sources": "0",
          "url": "/api/v2/inventories/75/"
        }
      },
      {
        "id": "6cc3a2d4-15d0-4b44-b299-45b6015c6a46",
        "kinds": [
          "ATOrganization"
        ],
        "properties": {
          "custom_virtualenv": "",
          "default_environment": "0",
          "description": "DEV ORG",
          "id": "14",
          "max_hosts": "0",
          "name": "DEV ORG",
          "url": "/api/v2/organizations/14/"
        }
      },
      {
        "id": "62ecf3b6-092c-4324-a323-64d6548a83d7",
        "kinds": [
          "ATOrganization"
        ],
        "properties": {
          "custom_virtualenv": "",
          "default_environment": "0",
          "description": "PROD ORG",
          "id": "15",
          "max_hosts": "0",
          "name": "PROD ORG",
          "url": "/api/v2/organizations/15/"
        }
      },
      {
        "id": "b4b9a957-5442-4d05-8a4e-ffbe0e084773",
        "kinds": [
          "ATCredential"
        ],
        "properties": {
          "cloud": "false",
          "credential_type": "19",
          "description": "",
          "id": "2",
          "kubernetes": "false",
          "managed": "true",
          "name": "Ansible Galaxy",
          "organization": "0",
          "url": "/api/v2/credentials/2/"
        }
      },
      {
        "id": "f80c1c30-8036-4ca5-9124-8ec5a8848648",
        "kinds": [
          "ATCredential"
        ],
        "properties": {
          "cloud": "false",
          "credential_type": "1",
          "description": "",
          "id": "94",
          "kubernetes": "false",
          "managed": "false",
          "name": "Backup",
          "organization": "15",
          "url": "/api/v2/credentials/94/"
        }
      },
      {
        "id": "eaea00b2-ab1f-40ed-a461-429697ea36db",
        "kinds": [
          "ATCredential"
        ],
        "properties": {
          "cloud": "false",
          "credential_type": "1",
          "description": "",
          "id": "91",
          "kubernetes": "false",
          "managed": "false",
          "name": "Dev",
          "organization": "14",
          "url": "/api/v2/credentials/91/"
        }
      },
      {
        "id": "d48673da-c8fc-4781-a8d6-adbcb8f8be7e",
        "kinds": [
          "ATCredential"
        ],
        "properties": {
          "cloud": "false",
          "credential_type": "11",
          "description": "",
          "id": "92",
          "kubernetes": "false",
          "managed": "false",
          "name": "GH Token",
          "organization": "0",
          "url": "/api/v2/credentials/92/"
        }
      },
      {
        "id": "e4a59e7e-d3e7-4e1b-9fc0-db7868ebdfa0",
        "kinds": [
          "ATCredential"
        ],
        "properties": {
          "cloud": "false",
          "credential_type": "1",
          "description": "",
          "id": "93",
          "kubernetes": "false",
          "managed": "false",
          "name": "Prod",
          "organization": "15",
          "url": "/api/v2/credentials/93/"
        }
      },
      {
        "id": "91907e05-f8bf-419f-b342-1f4c05d7bd11",
        "kinds": [
          "ATProject"
        ],
        "properties": {
          "allow_override": "false",
          "credential": "0",
          "custom_virtualenv": "",
          "default_environment": "0",
          "description": "",
          "id": "86",
          "last_job_failed": "false",
          "last_job_run": "2025-07-30T19:14:03.436437Z",
          "last_update": "2025-07-30T19:14:03.436437Z",
          "last_update_failed": "false",
          "local_path": "_86__projecta",
          "name": "DEPLOY",
          "next_job_run": "",
          "organization": "14",
          "scm_branch": "",
          "scm_clean": "false",
          "scm_delete_on_update": "false",
          "scm_ref_spec": "",
          "scm_revision": "42c93829ab9f566db2a05e5e2444279f697549a5",
          "scm_track_submodules": "false",
          "scm_type": "git",
          "scm_update_cache_timeout": "0",
          "scm_update_on_launch": "false",
          "scm_url": "https://github.com/ansible/tower-example",
          "signature_validation_credential": "0",
          "status": "successful",
          "timeout": "0",
          "url": "/api/v2/projects/86/"
        }
      },
      {
        "id": "3adf4339-50e6-4808-b90d-dbfc1b35b3b5",
        "kinds": [
          "ATProject"
        ],
        "properties": {
          "allow_override": "false",
          "credential": "0",
          "custom_virtualenv": "",
          "default_environment": "0",
          "description": "",
          "id": "87",
          "last_job_failed": "false",
          "last_job_run": "2025-07-30T19:14:30.248480Z",
          "last_update": "2025-07-30T19:14:30.248480Z",
          "last_update_failed": "false",
          "local_path": "_87__projectb",
          "name": "DEPLOY",
          "next_job_run": "",
          "organization": "15",
          "scm_branch": "",
          "scm_clean": "false",
          "scm_delete_on_update": "false",
          "scm_ref_spec": "",
          "scm_revision": "42c93829ab9f566db2a05e5e2444279f697549a5",
          "scm_track_submodules": "false",
          "scm_type": "git",
          "scm_update_cache_timeout": "0",
          "scm_update_on_launch": "false",
          "scm_url": "https://github.com/ansible/tower-example",
          "signature_validation_credential": "0",
          "status": "successful",
          "timeout": "0",
          "url": "/api/v2/projects/87/"
        }
      },
      {
        "id": "b4d6d2be-d347-46df-ab71-6c3eb95e4abd",
        "kinds": [
          "ATProject"
        ],
        "properties": {
          "allow_override": "false",
          "credential": "0",
          "custom_virtualenv": "",
          "default_environment": "0",
          "description": "",
          "id": "88",
          "last_job_failed": "false",
          "last_job_run": "2025-07-30T19:14:44.340132Z",
          "last_update": "2025-07-30T19:14:44.340132Z",
          "last_update_failed": "false",
          "local_path": "_88__projectc",
          "name": "BACKUP",
          "next_job_run": "",
          "organization": "15",
          "scm_branch": "",
          "scm_clean": "false",
          "scm_delete_on_update": "false",
          "scm_ref_spec": "",
          "scm_revision": "42c93829ab9f566db2a05e5e2444279f697549a5",
          "scm_track_submodules": "false",
          "scm_type": "git",
          "scm_update_cache_timeout": "0",
          "scm_update_on_launch": "false",
          "scm_url": "https://github.com/ansible/tower-example",
          "signature_validation_credential": "0",
          "status": "successful",
          "timeout": "0",
          "url": "/api/v2/projects/88/"
        }
      },
      {
        "id": "b949abb9-4345-4b94-ae8b-f8b19535f4cf",
        "kinds": [
          "ATTeam"
        ],
        "properties": {
          "created": "2025-07-30T19:07:16.266198Z",
          "description": "",
          "id": "4",
          "modified": "2025-07-30T19:07:16.266205Z",
          "name": "Ansible Support",
          "type": "team",
          "url": "/api/v2/teams/4/"
        }
      },
      {
        "id": "cd6d14e6-1754-4e8c-af1b-636a5c6beab7",
        "kinds": [
          "ATTeam"
        ],
        "properties": {
          "created": "2025-07-30T19:03:17.569550Z",
          "description": "",
          "id": "2",
          "modified": "2025-07-30T19:06:53.858578Z",
          "name": "Dev",
          "type": "team",
          "url": "/api/v2/teams/2/"
        }
      },
      {
        "id": "405ffeb6-aee9-4e64-b57f-cea946e6720b",
        "kinds": [
          "ATTeam"
        ],
        "properties": {
          "created": "2025-07-30T19:05:45.564916Z",
          "description": "",
          "id": "3",
          "modified": "2025-07-30T19:05:51.105328Z",
          "name": "Collaborator",
          "type": "team",
          "url": "/api/v2/teams/3/"
        }
      }
    ],
    "edges": [
      {
        "kind": "ATContains",
        "start": {
          "value": "6cc3a2d4-15d0-4b44-b299-45b6015c6a46",
          "match_by": "id"
        },
        "end": {
          "value": "e8d539b4-6435-407b-805f-20ce2723e272",
          "match_by": "id"
        }
      },
      {
        "kind": "ATContains",
        "start": {
          "value": "62ecf3b6-092c-4324-a323-64d6548a83d7",
          "match_by": "id"
        },
        "end": {
          "value": "2c4eeb63-0cf3-421d-bd13-3ec5eb5d6918",
          "match_by": "id"
        }
      },
      {
        "kind": "ATContains",
        "start": {
          "value": "e8d539b4-6435-407b-805f-20ce2723e272",
          "match_by": "id"
        },
        "end": {
          "value": "5f8bc352-f182-46d6-aa0e-ba61f1adb6ed",
          "match_by": "id"
        }
      },
      {
        "kind": "ATContains",
        "start": {
          "value": "e8d539b4-6435-407b-805f-20ce2723e272",
          "match_by": "id"
        },
        "end": {
          "value": "c2218a01-9d66-4ab0-a449-76bfebd957a3",
          "match_by": "id"
        }
      },
      {
        "kind": "ATContains",
        "start": {
          "value": "2c4eeb63-0cf3-421d-bd13-3ec5eb5d6918",
          "match_by": "id"
        },
        "end": {
          "value": "a4ae8ed6-e803-49cb-92f9-ab51fc747f04",
          "match_by": "id"
        }
      },
      {
        "kind": "ATContains",
        "start": {
          "value": "2c4eeb63-0cf3-421d-bd13-3ec5eb5d6918",
          "match_by": "id"
        },
        "end": {
          "value": "2363b88b-1009-4e61-aecc-c1d55e90d0dc",
          "match_by": "id"
        }
      },
      {
        "kind": "ATContains",
        "start": {
          "value": "2c4eeb63-0cf3-421d-bd13-3ec5eb5d6918",
          "match_by": "id"
        },
        "end": {
          "value": "e6cea985-10ce-447f-b487-7e7cf0f4960d",
          "match_by": "id"
        }
      },
      {
        "kind": "ATContains",
        "start": {
          "value": "62ecf3b6-092c-4324-a323-64d6548a83d7",
          "match_by": "id"
        },
        "end": {
          "value": "bbf3d527-f825-46fe-b24e-cc38fa083856",
          "match_by": "id"
        }
      },
      {
        "kind": "ATContains",
        "start": {
          "value": "6cc3a2d4-15d0-4b44-b299-45b6015c6a46",
          "match_by": "id"
        },
        "end": {
          "value": "bd1c786c-a802-4fe5-ba40-3e457415cf96",
          "match_by": "id"
        }
      },
      {
        "kind": "ATContains",
        "start": {
          "value": "62ecf3b6-092c-4324-a323-64d6548a83d7",
          "match_by": "id"
        },
        "end": {
          "value": "f4e5ba05-167e-4cae-a4fd-852976dafc79",
          "match_by": "id"
        }
      },
      {
        "kind": "ATContains",
        "start": {
          "value": "62ecf3b6-092c-4324-a323-64d6548a83d7",
          "match_by": "id"
        },
        "end": {
          "value": "f80c1c30-8036-4ca5-9124-8ec5a8848648",
          "match_by": "id"
        }
      },
      {
        "kind": "ATContains",
        "start": {
          "value": "6cc3a2d4-15d0-4b44-b299-45b6015c6a46",
          "match_by": "id"
        },
        "end": {
          "value": "eaea00b2-ab1f-40ed-a461-429697ea36db",
          "match_by": "id"
        }
      },
      {
        "kind": "ATContains",
        "start": {
          "value": "62ecf3b6-092c-4324-a323-64d6548a83d7",
          "match_by": "id"
        },
        "end": {
          "value": "e4a59e7e-d3e7-4e1b-9fc0-db7868ebdfa0",
          "match_by": "id"
        }
      },
      {
        "kind": "ATContains",
        "start": {
          "value": "6cc3a2d4-15d0-4b44-b299-45b6015c6a46",
          "match_by": "id"
        },
        "end": {
          "value": "91907e05-f8bf-419f-b342-1f4c05d7bd11",
          "match_by": "id"
        }
      },
      {
        "kind": "ATContains",
        "start": {
          "value": "62ecf3b6-092c-4324-a323-64d6548a83d7",
          "match_by": "id"
        },
        "end": {
          "value": "3adf4339-50e6-4808-b90d-dbfc1b35b3b5",
          "match_by": "id"
        }
      },
      {
        "kind": "ATContains",
        "start": {
          "value": "62ecf3b6-092c-4324-a323-64d6548a83d7",
          "match_by": "id"
        },
        "end": {
          "value": "b4d6d2be-d347-46df-ab71-6c3eb95e4abd",
          "match_by": "id"
        }
      },
      {
        "kind": "ATUses",
        "start": {
          "value": "bbf3d527-f825-46fe-b24e-cc38fa083856",
          "match_by": "id"
        },
        "end": {
          "value": "b4d6d2be-d347-46df-ab71-6c3eb95e4abd",
          "match_by": "id"
        }
      },
      {
        "kind": "ATUses",
        "start": {
          "value": "bd1c786c-a802-4fe5-ba40-3e457415cf96",
          "match_by": "id"
        },
        "end": {
          "value": "91907e05-f8bf-419f-b342-1f4c05d7bd11",
          "match_by": "id"
        }
      },
      {
        "kind": "ATUses",
        "start": {
          "value": "f4e5ba05-167e-4cae-a4fd-852976dafc79",
          "match_by": "id"
        },
        "end": {
          "value": "3adf4339-50e6-4808-b90d-dbfc1b35b3b5",
          "match_by": "id"
        }
      },
      {
        "kind": "ATUses",
        "start": {
          "value": "bbf3d527-f825-46fe-b24e-cc38fa083856",
          "match_by": "id"
        },
        "end": {
          "value": "2c4eeb63-0cf3-421d-bd13-3ec5eb5d6918",
          "match_by": "id"
        }
      },
      {
        "kind": "ATUses",
        "start": {
          "value": "bd1c786c-a802-4fe5-ba40-3e457415cf96",
          "match_by": "id"
        },
        "end": {
          "value": "e8d539b4-6435-407b-805f-20ce2723e272",
          "match_by": "id"
        }
      },
      {
        "kind": "ATUses",
        "start": {
          "value": "f4e5ba05-167e-4cae-a4fd-852976dafc79",
          "match_by": "id"
        },
        "end": {
          "value": "2c4eeb63-0cf3-421d-bd13-3ec5eb5d6918",
          "match_by": "id"
        }
      },
      {
        "kind": "ATMember",
        "start": {
          "value": "616715cc-1f67-445c-9318-d27c9ece349c",
          "match_by": "id"
        },
        "end": {
          "value": "cd6d14e6-1754-4e8c-af1b-636a5c6beab7",
          "match_by": "id"
        }
      },
      {
        "kind": "ATAdmin",
        "start": {
          "value": "126f49af-f1bb-4226-951c-09e2089964ed",
          "match_by": "id"
        },
        "end": {
          "value": "d48673da-c8fc-4781-a8d6-adbcb8f8be7e",
          "match_by": "id"
        }
      },
      {
        "kind": "ATMember",
        "start": {
          "value": "126f49af-f1bb-4226-951c-09e2089964ed",
          "match_by": "id"
        },
        "end": {
          "value": "62ecf3b6-092c-4324-a323-64d6548a83d7",
          "match_by": "id"
        }
      },
      {
        "kind": "ATMember",
        "start": {
          "value": "126f49af-f1bb-4226-951c-09e2089964ed",
          "match_by": "id"
        },
        "end": {
          "value": "b949abb9-4345-4b94-ae8b-f8b19535f4cf",
          "match_by": "id"
        }
      },
      {
        "kind": "ATMember",
        "start": {
          "value": "89ba387b-501f-4845-b5c9-0000fd1a1892",
          "match_by": "id"
        },
        "end": {
          "value": "62ecf3b6-092c-4324-a323-64d6548a83d7",
          "match_by": "id"
        }
      },
      {
        "kind": "ATMember",
        "start": {
          "value": "89ba387b-501f-4845-b5c9-0000fd1a1892",
          "match_by": "id"
        },
        "end": {
          "value": "405ffeb6-aee9-4e64-b57f-cea946e6720b",
          "match_by": "id"
        }
      },
      {
        "kind": "ATExecute",
        "start": {
          "value": "5b91f087-b5c2-46fd-9402-8c5b54476d01",
          "match_by": "id"
        },
        "end": {
          "value": "bbf3d527-f825-46fe-b24e-cc38fa083856",
          "match_by": "id"
        }
      },
      {
        "kind": "ATAdmin",
        "start": {
          "value": "5b91f087-b5c2-46fd-9402-8c5b54476d01",
          "match_by": "id"
        },
        "end": {
          "value": "f80c1c30-8036-4ca5-9124-8ec5a8848648",
          "match_by": "id"
        }
      },
      {
        "kind": "ATRead",
        "start": {
          "value": "5b91f087-b5c2-46fd-9402-8c5b54476d01",
          "match_by": "id"
        },
        "end": {
          "value": "2c4eeb63-0cf3-421d-bd13-3ec5eb5d6918",
          "match_by": "id"
        }
      },
      {
        "kind": "ATMember",
        "start": {
          "value": "5b91f087-b5c2-46fd-9402-8c5b54476d01",
          "match_by": "id"
        },
        "end": {
          "value": "62ecf3b6-092c-4324-a323-64d6548a83d7",
          "match_by": "id"
        }
      },
      {
        "kind": "ATExecute",
        "start": {
          "value": "b949abb9-4345-4b94-ae8b-f8b19535f4cf",
          "match_by": "id"
        },
        "end": {
          "value": "6cc3a2d4-15d0-4b44-b299-45b6015c6a46",
          "match_by": "id"
        }
      },
      {
        "kind": "ATProjectAdmin",
        "start": {
          "value": "b949abb9-4345-4b94-ae8b-f8b19535f4cf",
          "match_by": "id"
        },
        "end": {
          "value": "6cc3a2d4-15d0-4b44-b299-45b6015c6a46",
          "match_by": "id"
        }
      },
      {
        "kind": "ATInventoryAdmin",
        "start": {
          "value": "b949abb9-4345-4b94-ae8b-f8b19535f4cf",
          "match_by": "id"
        },
        "end": {
          "value": "6cc3a2d4-15d0-4b44-b299-45b6015c6a46",
          "match_by": "id"
        }
      },
      {
        "kind": "ATCredentialAdmin",
        "start": {
          "value": "b949abb9-4345-4b94-ae8b-f8b19535f4cf",
          "match_by": "id"
        },
        "end": {
          "value": "6cc3a2d4-15d0-4b44-b299-45b6015c6a46",
          "match_by": "id"
        }
      },
      {
        "kind": "ATWorkflowAdmin",
        "start": {
          "value": "b949abb9-4345-4b94-ae8b-f8b19535f4cf",
          "match_by": "id"
        },
        "end": {
          "value": "6cc3a2d4-15d0-4b44-b299-45b6015c6a46",
          "match_by": "id"
        }
      },
      {
        "kind": "ATNotificationAdmin",
        "start": {
          "value": "b949abb9-4345-4b94-ae8b-f8b19535f4cf",
          "match_by": "id"
        },
        "end": {
          "value": "6cc3a2d4-15d0-4b44-b299-45b6015c6a46",
          "match_by": "id"
        }
      },
      {
        "kind": "ATJobTemplateAdmin",
        "start": {
          "value": "b949abb9-4345-4b94-ae8b-f8b19535f4cf",
          "match_by": "id"
        },
        "end": {
          "value": "6cc3a2d4-15d0-4b44-b299-45b6015c6a46",
          "match_by": "id"
        }
      },
      {
        "kind": "ATExecutionEnvironmentAdmin",
        "start": {
          "value": "b949abb9-4345-4b94-ae8b-f8b19535f4cf",
          "match_by": "id"
        },
        "end": {
          "value": "6cc3a2d4-15d0-4b44-b299-45b6015c6a46",
          "match_by": "id"
        }
      },
      {
        "kind": "ATAuditor",
        "start": {
          "value": "b949abb9-4345-4b94-ae8b-f8b19535f4cf",
          "match_by": "id"
        },
        "end": {
          "value": "6cc3a2d4-15d0-4b44-b299-45b6015c6a46",
          "match_by": "id"
        }
      },
      {
        "kind": "ATRead",
        "start": {
          "value": "b949abb9-4345-4b94-ae8b-f8b19535f4cf",
          "match_by": "id"
        },
        "end": {
          "value": "6cc3a2d4-15d0-4b44-b299-45b6015c6a46",
          "match_by": "id"
        }
      },
      {
        "kind": "ATApprove",
        "start": {
          "value": "b949abb9-4345-4b94-ae8b-f8b19535f4cf",
          "match_by": "id"
        },
        "end": {
          "value": "6cc3a2d4-15d0-4b44-b299-45b6015c6a46",
          "match_by": "id"
        }
      },
      {
        "kind": "ATExecute",
        "start": {
          "value": "b949abb9-4345-4b94-ae8b-f8b19535f4cf",
          "match_by": "id"
        },
        "end": {
          "value": "62ecf3b6-092c-4324-a323-64d6548a83d7",
          "match_by": "id"
        }
      },
      {
        "kind": "ATProjectAdmin",
        "start": {
          "value": "b949abb9-4345-4b94-ae8b-f8b19535f4cf",
          "match_by": "id"
        },
        "end": {
          "value": "62ecf3b6-092c-4324-a323-64d6548a83d7",
          "match_by": "id"
        }
      },
      {
        "kind": "ATInventoryAdmin",
        "start": {
          "value": "b949abb9-4345-4b94-ae8b-f8b19535f4cf",
          "match_by": "id"
        },
        "end": {
          "value": "62ecf3b6-092c-4324-a323-64d6548a83d7",
          "match_by": "id"
        }
      },
      {
        "kind": "ATCredentialAdmin",
        "start": {
          "value": "b949abb9-4345-4b94-ae8b-f8b19535f4cf",
          "match_by": "id"
        },
        "end": {
          "value": "62ecf3b6-092c-4324-a323-64d6548a83d7",
          "match_by": "id"
        }
      },
      {
        "kind": "ATWorkflowAdmin",
        "start": {
          "value": "b949abb9-4345-4b94-ae8b-f8b19535f4cf",
          "match_by": "id"
        },
        "end": {
          "value": "62ecf3b6-092c-4324-a323-64d6548a83d7",
          "match_by": "id"
        }
      },
      {
        "kind": "ATNotificationAdmin",
        "start": {
          "value": "b949abb9-4345-4b94-ae8b-f8b19535f4cf",
          "match_by": "id"
        },
        "end": {
          "value": "62ecf3b6-092c-4324-a323-64d6548a83d7",
          "match_by": "id"
        }
      },
      {
        "kind": "ATJobTemplateAdmin",
        "start": {
          "value": "b949abb9-4345-4b94-ae8b-f8b19535f4cf",
          "match_by": "id"
        },
        "end": {
          "value": "62ecf3b6-092c-4324-a323-64d6548a83d7",
          "match_by": "id"
        }
      },
      {
        "kind": "ATExecutionEnvironmentAdmin",
        "start": {
          "value": "b949abb9-4345-4b94-ae8b-f8b19535f4cf",
          "match_by": "id"
        },
        "end": {
          "value": "62ecf3b6-092c-4324-a323-64d6548a83d7",
          "match_by": "id"
        }
      },
      {
        "kind": "ATAuditor",
        "start": {
          "value": "b949abb9-4345-4b94-ae8b-f8b19535f4cf",
          "match_by": "id"
        },
        "end": {
          "value": "62ecf3b6-092c-4324-a323-64d6548a83d7",
          "match_by": "id"
        }
      },
      {
        "kind": "ATRead",
        "start": {
          "value": "b949abb9-4345-4b94-ae8b-f8b19535f4cf",
          "match_by": "id"
        },
        "end": {
          "value": "62ecf3b6-092c-4324-a323-64d6548a83d7",
          "match_by": "id"
        }
      },
      {
        "kind": "ATApprove",
        "start": {
          "value": "b949abb9-4345-4b94-ae8b-f8b19535f4cf",
          "match_by": "id"
        },
        "end": {
          "value": "62ecf3b6-092c-4324-a323-64d6548a83d7",
          "match_by": "id"
        }
      },
      {
        "kind": "ATProjectAdmin",
        "start": {
          "value": "cd6d14e6-1754-4e8c-af1b-636a5c6beab7",
          "match_by": "id"
        },
        "end": {
          "value": "6cc3a2d4-15d0-4b44-b299-45b6015c6a46",
          "match_by": "id"
        }
      },
      {
        "kind": "ATInventoryAdmin",
        "start": {
          "value": "cd6d14e6-1754-4e8c-af1b-636a5c6beab7",
          "match_by": "id"
        },
        "end": {
          "value": "6cc3a2d4-15d0-4b44-b299-45b6015c6a46",
          "match_by": "id"
        }
      },
      {
        "kind": "ATCredentialAdmin",
        "start": {
          "value": "cd6d14e6-1754-4e8c-af1b-636a5c6beab7",
          "match_by": "id"
        },
        "end": {
          "value": "6cc3a2d4-15d0-4b44-b299-45b6015c6a46",
          "match_by": "id"
        }
      },
      {
        "kind": "ATWorkflowAdmin",
        "start": {
          "value": "cd6d14e6-1754-4e8c-af1b-636a5c6beab7",
          "match_by": "id"
        },
        "end": {
          "value": "6cc3a2d4-15d0-4b44-b299-45b6015c6a46",
          "match_by": "id"
        }
      },
      {
        "kind": "ATJobTemplateAdmin",
        "start": {
          "value": "cd6d14e6-1754-4e8c-af1b-636a5c6beab7",
          "match_by": "id"
        },
        "end": {
          "value": "6cc3a2d4-15d0-4b44-b299-45b6015c6a46",
          "match_by": "id"
        }
      },
      {
        "kind": "ATRead",
        "start": {
          "value": "cd6d14e6-1754-4e8c-af1b-636a5c6beab7",
          "match_by": "id"
        },
        "end": {
          "value": "6cc3a2d4-15d0-4b44-b299-45b6015c6a46",
          "match_by": "id"
        }
      },
      {
        "kind": "ATExecute",
        "start": {
          "value": "405ffeb6-aee9-4e64-b57f-cea946e6720b",
          "match_by": "id"
        },
        "end": {
          "value": "62ecf3b6-092c-4324-a323-64d6548a83d7",
          "match_by": "id"
        }
      }
    ]
  }
}